recurringdateutil.py
recurringdateutil-0.0.3.dist-info/METADATA
recurringdateutil-0.0.3.dist-info/WHEEL
recurringdateutil-0.0.3.dist-info/top_level.txt
recurringdateutil-0.0.3.dist-info/RECORD
