Metadata-Version: 2.1
Name: recurringdateutil
Version: 0.0.3
Summary: Custom Package for recurring date utility
Home-page: UNKNOWN
Author: Samar Chowdhury
License: UNKNOWN
Platform: UNKNOWN
Classifier: Programming Language :: Python :: 3
Classifier: License :: OSI Approved :: MIT License
Classifier: Operating System :: OS Independent
Requires-Python: >=3.6
